usfutils/__init__.py
usfutils/config.py
usfutils/dict.py
usfutils/dir.py
usfutils/dist.py
usfutils/format.py
usfutils/load.py
usfutils/logger.py
usfutils/statistics.py
usfutils/time.py
usfutils/utils.py
usfutils/version.py
usfutils-2.0.3.dist-info/LICENSE
usfutils-2.0.3.dist-info/METADATA
usfutils-2.0.3.dist-info/WHEEL
usfutils-2.0.3.dist-info/top_level.txt
usfutils-2.0.3.dist-info/RECORD
