Metadata-Version: 2.1
Name: usfutils
Version: 2.0.3
Summary: Open Source Universal Tool Library for Python Project
Home-page: https://github.com/chenaoxuan/UsfUtils.git
Author: AoXuan Chen
Author-email: cax1165@163.com
License: Apache License 2.0
Keywords: python,pytorch,utils
Classifier: Development Status :: 4 - Beta
Classifier: Operating System :: OS Independent
Classifier: License :: OSI Approved :: Apache Software License
Classifier: Programming Language :: Python :: 3
License-File: LICENSE
Requires-Dist: pyyaml
